{ 
	"tables": [{
			"typ" : "hugg",
			"table":{

					"name":"normal",
					"values" : [
						{"maxValue":33, "träffområde": "huvud", "delområde" : "ansikte"},
						{"maxValue":45, "träffområde": "huvud", "delområde" : "skalle"},
						{"maxValue":66, "träffområde": "huvud", "delområde" : "hals"},
						{"maxValue":100, "träffområde": "torso", "delområde" : "torso"}
					]
				}

			}, 
			{
				"typ" : "hugg",
				"table":{
						"name":"hög",
						"values" : [
							{"maxValue":50, "träffområde": "huvud", "delområde" : "ansikte"},
							{"maxValue":75, "träffområde": "huvud", "delområde" : "skalle"},
							{"maxValue":100, "träffområde": "huvud", "delområde" : "hals"}
							]
						}

				}
			
	]
}
